aio_aws/__init__.py
aio_aws/aio_aws_batch.py
aio_aws/aio_aws_batch_db.py
aio_aws/aio_aws_batch_manager.py
aio_aws/aio_aws_config.py
aio_aws/aio_aws_lambda.py
aio_aws/aio_aws_s3.py
aio_aws/async_executor.py
aio_aws/async_main.py
aio_aws/aws_batch_db.py
aio_aws/aws_batch_models.py
aio_aws/logger.py
aio_aws/s3_aio.py
aio_aws/s3_io.py
aio_aws/s3_uri.py
aio_aws/utils.py
aio_aws/uuid_utils.py
aio_aws/version.py
aio_aws-0.22.1.dist-info/LICENSE
aio_aws-0.22.1.dist-info/METADATA
aio_aws-0.22.1.dist-info/WHEEL
aio_aws-0.22.1.dist-info/RECORD
