Metadata-Version: 2.1
Name: aio-aws
Version: 0.22.1
Summary: aio-aws
Home-page: https://github.com/dazza-codes/aio-aws
License: Apache-2.0
Keywords: Development Status :: 3 - Alpha,Topic :: Utilities,Intended Audience :: Developers,Operating System :: OS Independent,Programming Language :: Python,Programming Language :: Python :: 3,Programming Language :: Python :: 3.8,Programming Language :: Python :: 3.9,Programming Language :: Python :: 3.10,Programming Language :: Python :: 3.11,Programming Language :: Python :: 3 :: Only,License :: OSI Approved :: Apache Software License
Author: Darren Weber
Author-email: dazza-codes@github.com
Requires-Python: >=3.8,<4.0
Classifier: License :: OSI Approved :: Apache Software License
Classifier: Programming Language :: Python :: 3
Classifier: Programming Language :: Python :: 3.8
Classifier: Programming Language :: Python :: 3.9
Classifier: Programming Language :: Python :: 3.10
Classifier: Programming Language :: Python :: 3.11
Provides-Extra: aioredis
Provides-Extra: all
Provides-Extra: databases
Provides-Extra: docs
Provides-Extra: redis
Requires-Dist: PyYAML (>=5.2,<6.0)
Requires-Dist: Sphinx (>=5.0,<6.0) ; extra == "docs"
Requires-Dist: aiofiles (>=22.0,<23.0)
Requires-Dist: databases[mysql,postgresql,sqlite] ; extra == "all" or extra == "databases"
Requires-Dist: ipython (>=8.0,<9.0) ; extra == "docs"
Requires-Dist: pydantic (>=1.10,<2.0)
Requires-Dist: redis[hiredis] (>=4.0,<5.0) ; extra == "all" or extra == "redis" or extra == "aioredis"
Requires-Dist: requests (>=2.0,<3.0)
Requires-Dist: s3fs[awscli,boto3] (>=2023.0,<2024.0)
Requires-Dist: sphinx-autoapi (>=2.0,<3.0) ; extra == "docs"
Requires-Dist: sphinx-autodoc-typehints (>=1.0,<2.0) ; extra == "docs"
Requires-Dist: sphinx-rtd-theme (>=1.0,<2.0) ; extra == "docs"
Requires-Dist: tinydb (>=4.0,<5.0)
Project-URL: Repository, https://github.com/dazza-codes/aio-aws.git
